wiever/__init__.py
wiever/commands/version_commands.py
wiever/commands/viewer/__init__.py
wiever/commands/viewer/ascii.py
wiever/commands/viewer/base_command.py
wiever/core/cli.py
wiever/core/viewer/__init__.py
wiever/core/viewer/ascii_tree.py
wiever/main.py
wiever-0.1.1.dist-info/LICENSE
wiever-0.1.1.dist-info/METADATA
wiever-0.1.1.dist-info/WHEEL
wiever-0.1.1.dist-info/entry_points.txt
wiever-0.1.1.dist-info/RECORD
